setup.cfg
setup.py
saladware/SaladColor.py
saladware/__init__.py
saladware/dscrd.py
saladware.egg-info/PKG-INFO
saladware.egg-info/SOURCES.txt
saladware.egg-info/dependency_links.txt
saladware.egg-info/not-zip-safe
saladware.egg-info/top_level.txt