Metadata-Version: 1.0
Name: saladware
Version: 0.5.6.1
Summary: two bears
Home-page: UNKNOWN
Author: SALAD37
Author-email: nonemovo@gmail.com
License: MIT
Platform: UNKNOWN
